bpusdk/__init__.py
bpusdk/BrainpyLib/BrainpyBase.pyc
bpusdk/BrainpyLib/Common.pyc
bpusdk/BrainpyLib/GenConn.pyc
bpusdk/BrainpyLib/SpikeWriter.pyc
bpusdk/BrainpyLib/UpdateRule.pyc
bpusdk/BrainpyLib/__init__.py
bpusdk/BrainpyLib/lb1_SNN.pyc
bpusdk/BrainpyLib/lb1_checkRes.pyc
bpusdk/BrainpyLib/lb1_deploy.pyc
bpusdk/BrainpyLib/lb2_SNN.pyc
bpusdk/BrainpyLib/lb2_checkRes.pyc
bpusdk/BrainpyLib/lb2_deploy.pyc
bpusdk/BrainpyLib/util.pyc
bpusdk/BrainpyLib/__pycache__/BrainpyBase.cpython-310.pyc
bpusdk/BrainpyLib/__pycache__/Common.cpython-310.pyc
bpusdk/BrainpyLib/__pycache__/GenConn.cpython-310.pyc
bpusdk/BrainpyLib/__pycache__/SpikeWriter.cpython-310.pyc
bpusdk/BrainpyLib/__pycache__/UpdateRule.cpython-310.pyc
bpusdk/BrainpyLib/__pycache__/__init__.cpython-310.pyc
bpusdk/BrainpyLib/__pycache__/lb2_SNN.cpython-310.pyc
bpusdk/BrainpyLib/__pycache__/lb2_checkRes.cpython-310.pyc
bpusdk/BrainpyLib/__pycache__/lb2_deploy.cpython-310.pyc
bpusdk/Mapping/Router.pyc
bpusdk/Mapping/W2H.pyc
bpusdk/Mapping/__init__.py
bpusdk/Mapping/lb1_weight.pyc
bpusdk/Mapping/lb2_weight.pyc
bpusdk/Mapping/lb2_weight_matrix.pyc
bpusdk/Mapping/lb2_weight_pool.pyc
bpusdk/Mapping/__pycache__/Router.cpython-310.pyc
bpusdk/Mapping/__pycache__/W2H.cpython-310.pyc
bpusdk/Mapping/__pycache__/__init__.cpython-310.pyc
bpusdk/Mapping/__pycache__/lb2_weight.cpython-310.pyc
bpusdk/Models/EImodel.py
bpusdk/Models/EImodel_AdQuaIF.py
bpusdk/Models/EImodel_ExpIF.py
bpusdk/Models/EImodel_HH.py
bpusdk/Models/EImodel_HHtemp.py
bpusdk/Models/EImodel_Izhikevich.py
bpusdk/Models/EImodel_basic.py
bpusdk/Models/EImodel_basic_v2.py
bpusdk/Models/EImodel_debug.py
bpusdk/Models/EImodel_lb1_int8.py
bpusdk/Models/EImodel_lb2_int8.py
bpusdk/Models/EImodel_legancy.py
bpusdk/Models/EImodel_singleSyn.py
bpusdk/Models/Emodel_lb1_int8_legency.py
bpusdk/Models/Emodel_lb1_int8_time_dump.py
bpusdk/Models/__init__.py
bpusdk/Models/neuron4EIModel.py
bpusdk/SNNCompiler/__init__.py
bpusdk/SNNCompiler/lb1_Compiler.pyc
bpusdk-5.2.dist-info/METADATA
bpusdk-5.2.dist-info/WHEEL
bpusdk-5.2.dist-info/top_level.txt
bpusdk-5.2.dist-info/RECORD
