Metadata-Version: 2.4
Name: bpusdk
Version: 5.2
Author: GDIIST
Author-email: 739503445@qq.com
License: MIT
Requires-Dist: brainpy>=2.4.2
Requires-Dist: brainpylib
Dynamic: author
Dynamic: author-email
Dynamic: license
Dynamic: requires-dist
